decorest/DELETE.py
decorest/GET.py
decorest/HEAD.py
decorest/OPTIONS.py
decorest/PATCH.py
decorest/POST.py
decorest/PUT.py
decorest/__init__.py
decorest/client.py
decorest/decorator_utils.py
decorest/decorators.py
decorest/errors.py
decorest/request.py
decorest/session.py
decorest/types.py
decorest/utils.py
examples/__init__.py
examples/httpbin/__init__.py
examples/httpbin/httpbin_async_client.py
examples/httpbin/httpbin_client.py
examples/httpbin/httpbin_client_with_typing.py
examples/swagger_petstore/__init__.py
examples/swagger_petstore/petstore_client.py
examples/swagger_petstore/petstore_client_with_typing.py
decorest-0.1.0.dist-info/AUTHORS
decorest-0.1.0.dist-info/LICENSE
decorest-0.1.0.dist-info/METADATA
decorest-0.1.0.dist-info/WHEEL
decorest-0.1.0.dist-info/top_level.txt
decorest-0.1.0.dist-info/RECORD
