Metadata-Version: 2.1
Name: decorest
Version: 0.1.0
Summary: `decorest` library provides an easy to use declarative REST API client interface, where definition of the API methods using decorators automatically gives a working REST client with no additional code.
Home-page: https://github.com/bkryza/decorest
Author: Bartek Kryza
Author-email: bkryza@gmail.com
License: Apache 2.0
Platform: UNKNOWN
Classifier: Development Status :: 4 - Beta
Classifier: Intended Audience :: Developers
Classifier: Natural Language :: English
Classifier: License :: OSI Approved :: Apache Software License
Classifier: Operating System :: OS Independent
Classifier: Programming Language :: Python
Classifier: Programming Language :: Python :: 3.6
Classifier: Programming Language :: Python :: 3.7
Classifier: Programming Language :: Python :: 3.8
Classifier: Programming Language :: Python :: 3.9
Classifier: Programming Language :: Python :: 3.10
Requires-Dist: requests
Requires-Dist: requests-toolbelt
